create_py_app/__init__.py
create_py_app/cli.py
py_create_app-0.1.4.dist-info/licenses/LICENSE
py_create_app-0.1.4.dist-info/METADATA
py_create_app-0.1.4.dist-info/WHEEL
py_create_app-0.1.4.dist-info/entry_points.txt
py_create_app-0.1.4.dist-info/top_level.txt
py_create_app-0.1.4.dist-info/RECORD
